{
  "Parent": "Glyph_Template",
  "Title": "Resonate",
  "Description": "Appends a parallel glyph chain to an ally's active hex construct. Can transfer mana to the construct's owner or directly to entities with a mana pool.",
  "ModelPath": "Resonate",
  "BasePower": 1.0,
  "ManaConsumption": 12,
  "ShapeStructure": [
    {
      "ShapeId": "Antisquare",
      "Size": 1.0
    },
    {
      "ShapeId": "Circle",
      "Size": 0.8
    }
  ],
  "Slots": {
    "target": {
      "Style": "Input",
      "Label": "Target",
      "Description": "Hex construct entities to resonate with"
    },
    "mana": {
      "Style": "Input",
      "Label": "Mana",
      "Description": "Percentage of caster mana to transfer to target (0-100)"
    },
    "Next": {
      "Style": "Next",
      "Label": "Next",
      "Description": "The next glyph in the execution chain"
    }
  },
  "VolatilityCost": 4
}
