{
  "Parent": "Base_Glyph",
  "Title": "Equal",
  "Description": "Branches execution if A equals B. Assigns A to output if B is absent.",
  "GlyphType": "Hybrid",
  "ModelPath": "Glyph_Equal",
  "BasePower": 0,
  "ManaConsumption": 0,
  "Inputs": {
    "a": { "Title": "A", "DefaultSlot": 1, "Description": "First operand or value to assign" },
    "b": { "Title": "B", "Description": "Second operand (omit for assignment mode)" }
  },
  "Outputs": {
    "result": { "Title": "Result", "DefaultSlot": 2, "Description": "Variable slot to store the assigned value" }
  },
  "ShapeStructure": [
    { "ShapeId": "Antiline", "Size": 1.0 },
    { "ShapeId": "Antiline", "Size": 1.0 }
  ]
}
